oms_cms/__init__.py
oms_cms/backend/__init__.py
oms_cms/backend/api/__init__.py
oms_cms/backend/api/v1/__init__.py
oms_cms/backend/api/v1/urls.py
oms_cms/backend/api/v1/contact/__init__.py
oms_cms/backend/api/v1/contact/serializers.py
oms_cms/backend/api/v1/contact/urls.py
oms_cms/backend/api/v1/contact/views.py
oms_cms/backend/api/v1/info_block/__init__.py
oms_cms/backend/api/v1/info_block/serializers.py
oms_cms/backend/api/v1/info_block/urls.py
oms_cms/backend/api/v1/info_block/views.py
oms_cms/backend/api/v1/menu/__init__.py
oms_cms/backend/api/v1/menu/serializers.py
oms_cms/backend/api/v1/menu/urls.py
oms_cms/backend/api/v1/menu/views.py
oms_cms/backend/api/v1/news/__init__.py
oms_cms/backend/api/v1/news/serializers.py
oms_cms/backend/api/v1/news/urls.py
oms_cms/backend/api/v1/news/views.py
oms_cms/backend/api/v1/partners/__init__.py
oms_cms/backend/api/v1/partners/serializers.py
oms_cms/backend/api/v1/partners/urls.py
oms_cms/backend/api/v1/partners/views.py
oms_cms/backend/api/v1/photologue/__init__.py
oms_cms/backend/api/v1/photologue/serializers.py
oms_cms/backend/api/v1/photologue/urls.py
oms_cms/backend/api/v1/photologue/views.py
oms_cms/backend/api/v1/social_networks/__init__.py
oms_cms/backend/api/v1/social_networks/serializers.py
oms_cms/backend/api/v1/video/__init__.py
oms_cms/backend/api/v1/video/serializers.py
oms_cms/backend/api/v1/video/urls.py
oms_cms/backend/api/v1/video/views.py
oms_cms/backend/api/v2/urls.py
oms_cms/backend/api/v2/news/__init__.py
oms_cms/backend/api/v2/news/serializers.py
oms_cms/backend/api/v2/news/urls.py
oms_cms/backend/api/v2/news/views.py
oms_cms/backend/comments/__init__.py
oms_cms/backend/comments/admin.py
oms_cms/backend/comments/apps.py
oms_cms/backend/comments/forms.py
oms_cms/backend/comments/models.py
oms_cms/backend/comments/tests.py
oms_cms/backend/comments/urls.py
oms_cms/backend/comments/views.py
oms_cms/backend/comments/locale/en/LC_MESSAGES/django.mo
oms_cms/backend/comments/locale/en/LC_MESSAGES/django.po
oms_cms-0.9.9.dist-info/LICENSE
oms_cms-0.9.9.dist-info/METADATA
oms_cms-0.9.9.dist-info/WHEEL
oms_cms-0.9.9.dist-info/entry_points.txt
oms_cms-0.9.9.dist-info/top_level.txt
oms_cms-0.9.9.dist-info/RECORD
